ggames/__init__.py
ggames/cops_robbers_game.py
ggames/reachability_game.py
ggames-1.0.1.dist-info/LICENSE
ggames-1.0.1.dist-info/METADATA
ggames-1.0.1.dist-info/WHEEL
ggames-1.0.1.dist-info/entry_points.txt
ggames-1.0.1.dist-info/top_level.txt
ggames-1.0.1.dist-info/RECORD
