Metadata-Version: 2.1
Name: ggames
Version: 1.0.1
Summary: A package composed of tools for different games played on graph.
Home-page: https://github.com/gfl-math-stat-info/ggames
Author: Gabriel Fortin-Leblanc
Author-email: gabriel.fortin-leblanc@umontreal.ca
License: UNKNOWN
Platform: UNKNOWN
License-File: LICENSE
